Metadata-Version: 2.1
Name: mp3get
Version: 0.3.0
Summary: My short description for my project.
Home-page: https://github.com/hsw1020/mp3get/tree/master
Author: wsh
Author-email: w4hao@sina.com
License: MIT
Platform: UNKNOWN
Classifier: License :: OSI Approved :: MIT License
Classifier: Programming Language :: Python
Classifier: Programming Language :: Python :: 3
Classifier: Programming Language :: Python :: 3.6
Classifier: Programming Language :: Python :: Implementation :: CPython
Classifier: Programming Language :: Python :: Implementation :: PyPy
Requires-Python: >=3.5.0
License-File: LICENSE
